MANIFEST.in
README
fqueue.py
setup.py
fqueue.egg-info/PKG-INFO
fqueue.egg-info/SOURCES.txt
fqueue.egg-info/dependency_links.txt
fqueue.egg-info/top_level.txt