Metadata-Version: 1.1
Name: fqueue
Version: 0.0.6
Summary: Plain file based queue service
Home-page: https://github.com/lyxint/fqueue
Author: Elyes Du
Author-email: lyxint@gmail.com
License: UNKNOWN
Keywords: queue
Platform: UNKNOWN
Classifier: Development Status :: 4 - Beta
Classifier: Environment :: Console
Classifier: Intended Audience :: Developers
Classifier: Operating System :: POSIX
Classifier: Operating System :: POSIX :: Linux
Classifier: Programming Language :: Python
Classifier: Topic :: Software Development :: Libraries :: Python Modules
